<annotation verified="yes">
	<folder>catsanddogs</folder>
	<filename>dog.21.jpg</filename>
	<path>C:\catnd\train\catsanddogs\dog.21.jpg</path>
	<source>
		<database>Unknown</database>
	</source>
	<size>
		<width>415</width>
		<height>499</height>
		<depth>3</depth>
	</size>
	<segmented>0</segmented>
	<object>
		<name>dog</name>
		<pose>Unspecified</pose>
		<truncated>1</truncated>
		<difficult>0</difficult>
		<bndbox>
			<xmin>33</xmin>
			<ymin>36</ymin>
			<xmax>415</xmax>
			<ymax>499</ymax>
		</bndbox>
	</object>
</annotation>
